LICENSE.txt
MANIFEST.in
README.txt
setup.py
pcart_search/__init__.py
pcart_search/apps.py
pcart_search/backend.py
pcart_search/cms_apps.py
pcart_search/urls.py
pcart_search/views.py
pcart_search.egg-info/PKG-INFO
pcart_search.egg-info/SOURCES.txt
pcart_search.egg-info/dependency_links.txt
pcart_search.egg-info/not-zip-safe
pcart_search.egg-info/requires.txt
pcart_search.egg-info/top_level.txt
pcart_search/locale/ru/LC_MESSAGES/django.mo
pcart_search/locale/ru/LC_MESSAGES/django.po
pcart_search/locale/uk/LC_MESSAGES/django.mo
pcart_search/locale/uk/LC_MESSAGES/django.po